{"nodes": [{"id": "c_projects_ui_optimization_trip_sync_mobile_src_context_authcontext_tsx", "label": "AuthContext.tsx", "file_type": "code", "source_file": "C:\\projects\\ui optimization\\Trip-Sync\\mobile\\src\\context\\AuthContext.tsx", "source_location": "L1"}, {"id": "authcontext_authprovider", "label": "AuthProvider()", "file_type": "code", "source_file": "C:\\projects\\ui optimization\\Trip-Sync\\mobile\\src\\context\\AuthContext.tsx", "source_location": "L41"}], "edges": [{"source": "c_projects_ui_optimization_trip_sync_mobile_src_context_authcontext_tsx", "target": "react", "relation": "imports_from", "confidence": "EXTRACTED", "source_file": "C:\\projects\\ui optimization\\Trip-Sync\\mobile\\src\\context\\AuthContext.tsx", "source_location": "L1", "weight": 1.0}, {"source": "c_projects_ui_optimization_trip_sync_mobile_src_context_authcontext_tsx", "target": "async_storage", "relation": "imports_from", "confidence": "EXTRACTED", "source_file": "C:\\projects\\ui optimization\\Trip-Sync\\mobile\\src\\context\\AuthContext.tsx", "source_location": "L9", "weight": 1.0}, {"source": "c_projects_ui_optimization_trip_sync_mobile_src_context_authcontext_tsx", "target": "c_projects_ui_optimization_trip_sync_mobile_src_types", "relation": "imports_from", "confidence": "EXTRACTED", "source_file": "C:\\projects\\ui optimization\\Trip-Sync\\mobile\\src\\context\\AuthContext.tsx", "source_location": "L10", "weight": 1.0}, {"source": "c_projects_ui_optimization_trip_sync_mobile_src_context_authcontext_tsx", "target": "c_projects_ui_optimization_trip_sync_mobile_src_api_client", "relation": "imports_from", "confidence": "EXTRACTED", "source_file": "C:\\projects\\ui optimization\\Trip-Sync\\mobile\\src\\context\\AuthContext.tsx", "source_location": "L11", "weight": 1.0}, {"source": "c_projects_ui_optimization_trip_sync_mobile_src_context_authcontext_tsx", "target": "c_projects_ui_optimization_trip_sync_mobile_src_lib_supabase", "relation": "imports_from", "confidence": "EXTRACTED", "source_file": "C:\\projects\\ui optimization\\Trip-Sync\\mobile\\src\\context\\AuthContext.tsx", "source_location": "L12", "weight": 1.0}, {"source": "c_projects_ui_optimization_trip_sync_mobile_src_context_authcontext_tsx", "target": "authcontext_authprovider", "relation": "contains", "confidence": "EXTRACTED", "source_file": "C:\\projects\\ui optimization\\Trip-Sync\\mobile\\src\\context\\AuthContext.tsx", "source_location": "L41", "weight": 1.0}], "raw_calls": [{"caller_nid": "authcontext_authprovider", "callee": "useState", "source_file": "C:\\projects\\ui optimization\\Trip-Sync\\mobile\\src\\context\\AuthContext.tsx", "source_location": "L42"}, {"caller_nid": "authcontext_authprovider", "callee": "useState", "source_file": "C:\\projects\\ui optimization\\Trip-Sync\\mobile\\src\\context\\AuthContext.tsx", "source_location": "L43"}, {"caller_nid": "authcontext_authprovider", "callee": "useState", "source_file": "C:\\projects\\ui optimization\\Trip-Sync\\mobile\\src\\context\\AuthContext.tsx", "source_location": "L44"}, {"caller_nid": "authcontext_authprovider", "callee": "useEffect", "source_file": "C:\\projects\\ui optimization\\Trip-Sync\\mobile\\src\\context\\AuthContext.tsx", "source_location": "L46"}, {"caller_nid": "authcontext_authprovider", "callee": "useEffect", "source_file": "C:\\projects\\ui optimization\\Trip-Sync\\mobile\\src\\context\\AuthContext.tsx", "source_location": "L66"}, {"caller_nid": "authcontext_authprovider", "callee": "useCallback", "source_file": "C:\\projects\\ui optimization\\Trip-Sync\\mobile\\src\\context\\AuthContext.tsx", "source_location": "L104"}, {"caller_nid": "authcontext_authprovider", "callee": "useCallback", "source_file": "C:\\projects\\ui optimization\\Trip-Sync\\mobile\\src\\context\\AuthContext.tsx", "source_location": "L121"}, {"caller_nid": "authcontext_authprovider", "callee": "useCallback", "source_file": "C:\\projects\\ui optimization\\Trip-Sync\\mobile\\src\\context\\AuthContext.tsx", "source_location": "L148"}, {"caller_nid": "authcontext_authprovider", "callee": "useCallback", "source_file": "C:\\projects\\ui optimization\\Trip-Sync\\mobile\\src\\context\\AuthContext.tsx", "source_location": "L184"}, {"caller_nid": "authcontext_authprovider", "callee": "useCallback", "source_file": "C:\\projects\\ui optimization\\Trip-Sync\\mobile\\src\\context\\AuthContext.tsx", "source_location": "L195"}, {"caller_nid": "authcontext_authprovider", "callee": "useCallback", "source_file": "C:\\projects\\ui optimization\\Trip-Sync\\mobile\\src\\context\\AuthContext.tsx", "source_location": "L206"}, {"caller_nid": "authcontext_authprovider", "callee": "useMemo", "source_file": "C:\\projects\\ui optimization\\Trip-Sync\\mobile\\src\\context\\AuthContext.tsx", "source_location": "L218"}, {"caller_nid": "authcontext_authprovider", "callee": "useContext", "source_file": "C:\\projects\\ui optimization\\Trip-Sync\\mobile\\src\\context\\AuthContext.tsx", "source_location": "L227"}]}