{"nodes": [{"id": "c_projects_ui_optimization_trip_sync_mobile_src_lib_voicemanagerstub_ts", "label": "voiceManagerStub.ts", "file_type": "code", "source_file": "C:\\projects\\ui optimization\\Trip-Sync\\mobile\\src\\lib\\voiceManagerStub.ts", "source_location": "L1"}, {"id": "voicemanagerstub_stubvoicemanager", "label": "StubVoiceManager", "file_type": "code", "source_file": "C:\\projects\\ui optimization\\Trip-Sync\\mobile\\src\\lib\\voiceManagerStub.ts", "source_location": "L7"}, {"id": "voicemanagerstub_stubvoicemanager_constructor", "label": ".constructor()", "file_type": "code", "source_file": "C:\\projects\\ui optimization\\Trip-Sync\\mobile\\src\\lib\\voiceManagerStub.ts", "source_location": "L12"}, {"id": "voicemanagerstub_stubvoicemanager_start", "label": ".start()", "file_type": "code", "source_file": "C:\\projects\\ui optimization\\Trip-Sync\\mobile\\src\\lib\\voiceManagerStub.ts", "source_location": "L17"}, {"id": "voicemanagerstub_stubvoicemanager_stop", "label": ".stop()", "file_type": "code", "source_file": "C:\\projects\\ui optimization\\Trip-Sync\\mobile\\src\\lib\\voiceManagerStub.ts", "source_location": "L23"}, {"id": "voicemanagerstub_stubvoicemanager_callrider", "label": ".callRider()", "file_type": "code", "source_file": "C:\\projects\\ui optimization\\Trip-Sync\\mobile\\src\\lib\\voiceManagerStub.ts", "source_location": "L25"}, {"id": "voicemanagerstub_stubvoicemanager_handleoffer", "label": ".handleOffer()", "file_type": "code", "source_file": "C:\\projects\\ui optimization\\Trip-Sync\\mobile\\src\\lib\\voiceManagerStub.ts", "source_location": "L27"}, {"id": "voicemanagerstub_stubvoicemanager_handleanswer", "label": ".handleAnswer()", "file_type": "code", "source_file": "C:\\projects\\ui optimization\\Trip-Sync\\mobile\\src\\lib\\voiceManagerStub.ts", "source_location": "L29"}, {"id": "voicemanagerstub_stubvoicemanager_handleicecandidate", "label": ".handleIceCandidate()", "file_type": "code", "source_file": "C:\\projects\\ui optimization\\Trip-Sync\\mobile\\src\\lib\\voiceManagerStub.ts", "source_location": "L31"}, {"id": "voicemanagerstub_stubvoicemanager_removerider", "label": ".removeRider()", "file_type": "code", "source_file": "C:\\projects\\ui optimization\\Trip-Sync\\mobile\\src\\lib\\voiceManagerStub.ts", "source_location": "L33"}, {"id": "voicemanagerstub_stubvoicemanager_setmuted", "label": ".setMuted()", "file_type": "code", "source_file": "C:\\projects\\ui optimization\\Trip-Sync\\mobile\\src\\lib\\voiceManagerStub.ts", "source_location": "L35"}, {"id": "voicemanagerstub_stubvoicemanager_getmuted", "label": ".getMuted()", "file_type": "code", "source_file": "C:\\projects\\ui optimization\\Trip-Sync\\mobile\\src\\lib\\voiceManagerStub.ts", "source_location": "L37"}, {"id": "voicemanagerstub_stubvoicemanager_setvoicemode", "label": ".setVoiceMode()", "file_type": "code", "source_file": "C:\\projects\\ui optimization\\Trip-Sync\\mobile\\src\\lib\\voiceManagerStub.ts", "source_location": "L41"}, {"id": "voicemanagerstub_stubvoicemanager_setblocked", "label": ".setBlocked()", "file_type": "code", "source_file": "C:\\projects\\ui optimization\\Trip-Sync\\mobile\\src\\lib\\voiceManagerStub.ts", "source_location": "L43"}, {"id": "voicemanagerstub_stubvoicemanager_setremotemuted", "label": ".setRemoteMuted()", "file_type": "code", "source_file": "C:\\projects\\ui optimization\\Trip-Sync\\mobile\\src\\lib\\voiceManagerStub.ts", "source_location": "L45"}, {"id": "voicemanagerstub_stubvoicemanager_getconnectedriders", "label": ".getConnectedRiders()", "file_type": "code", "source_file": "C:\\projects\\ui optimization\\Trip-Sync\\mobile\\src\\lib\\voiceManagerStub.ts", "source_location": "L47"}], "edges": [{"source": "c_projects_ui_optimization_trip_sync_mobile_src_lib_voicemanagerstub_ts", "target": "c_projects_ui_optimization_trip_sync_mobile_src_lib_voicemanagertypes", "relation": "imports_from", "confidence": "EXTRACTED", "source_file": "C:\\projects\\ui optimization\\Trip-Sync\\mobile\\src\\lib\\voiceManagerStub.ts", "source_location": "L5", "weight": 1.0}, {"source": "c_projects_ui_optimization_trip_sync_mobile_src_lib_voicemanagerstub_ts", "target": "voicemanagerstub_stubvoicemanager", "relation": "contains", "confidence": "EXTRACTED", "source_file": "C:\\projects\\ui optimization\\Trip-Sync\\mobile\\src\\lib\\voiceManagerStub.ts", "source_location": "L7", "weight": 1.0}, {"source": "voicemanagerstub_stubvoicemanager", "target": "voicemanagerstub_stubvoicemanager_constructor", "relation": "method", "confidence": "EXTRACTED", "source_file": "C:\\projects\\ui optimization\\Trip-Sync\\mobile\\src\\lib\\voiceManagerStub.ts", "source_location": "L12", "weight": 1.0}, {"source": "voicemanagerstub_stubvoicemanager", "target": "voicemanagerstub_stubvoicemanager_start", "relation": "method", "confidence": "EXTRACTED", "source_file": "C:\\projects\\ui optimization\\Trip-Sync\\mobile\\src\\lib\\voiceManagerStub.ts", "source_location": "L17", "weight": 1.0}, {"source": "voicemanagerstub_stubvoicemanager", "target": "voicemanagerstub_stubvoicemanager_stop", "relation": "method", "confidence": "EXTRACTED", "source_file": "C:\\projects\\ui optimization\\Trip-Sync\\mobile\\src\\lib\\voiceManagerStub.ts", "source_location": "L23", "weight": 1.0}, {"source": "voicemanagerstub_stubvoicemanager", "target": "voicemanagerstub_stubvoicemanager_callrider", "relation": "method", "confidence": "EXTRACTED", "source_file": "C:\\projects\\ui optimization\\Trip-Sync\\mobile\\src\\lib\\voiceManagerStub.ts", "source_location": "L25", "weight": 1.0}, {"source": "voicemanagerstub_stubvoicemanager", "target": "voicemanagerstub_stubvoicemanager_handleoffer", "relation": "method", "confidence": "EXTRACTED", "source_file": "C:\\projects\\ui optimization\\Trip-Sync\\mobile\\src\\lib\\voiceManagerStub.ts", "source_location": "L27", "weight": 1.0}, {"source": "voicemanagerstub_stubvoicemanager", "target": "voicemanagerstub_stubvoicemanager_handleanswer", "relation": "method", "confidence": "EXTRACTED", "source_file": "C:\\projects\\ui optimization\\Trip-Sync\\mobile\\src\\lib\\voiceManagerStub.ts", "source_location": "L29", "weight": 1.0}, {"source": "voicemanagerstub_stubvoicemanager", "target": "voicemanagerstub_stubvoicemanager_handleicecandidate", "relation": "method", "confidence": "EXTRACTED", "source_file": "C:\\projects\\ui optimization\\Trip-Sync\\mobile\\src\\lib\\voiceManagerStub.ts", "source_location": "L31", "weight": 1.0}, {"source": "voicemanagerstub_stubvoicemanager", "target": "voicemanagerstub_stubvoicemanager_removerider", "relation": "method", "confidence": "EXTRACTED", "source_file": "C:\\projects\\ui optimization\\Trip-Sync\\mobile\\src\\lib\\voiceManagerStub.ts", "source_location": "L33", "weight": 1.0}, {"source": "voicemanagerstub_stubvoicemanager", "target": "voicemanagerstub_stubvoicemanager_setmuted", "relation": "method", "confidence": "EXTRACTED", "source_file": "C:\\projects\\ui optimization\\Trip-Sync\\mobile\\src\\lib\\voiceManagerStub.ts", "source_location": "L35", "weight": 1.0}, {"source": "voicemanagerstub_stubvoicemanager", "target": "voicemanagerstub_stubvoicemanager_getmuted", "relation": "method", "confidence": "EXTRACTED", "source_file": "C:\\projects\\ui optimization\\Trip-Sync\\mobile\\src\\lib\\voiceManagerStub.ts", "source_location": "L37", "weight": 1.0}, {"source": "voicemanagerstub_stubvoicemanager", "target": "voicemanagerstub_stubvoicemanager_setvoicemode", "relation": "method", "confidence": "EXTRACTED", "source_file": "C:\\projects\\ui optimization\\Trip-Sync\\mobile\\src\\lib\\voiceManagerStub.ts", "source_location": "L41", "weight": 1.0}, {"source": "voicemanagerstub_stubvoicemanager", "target": "voicemanagerstub_stubvoicemanager_setblocked", "relation": "method", "confidence": "EXTRACTED", "source_file": "C:\\projects\\ui optimization\\Trip-Sync\\mobile\\src\\lib\\voiceManagerStub.ts", "source_location": "L43", "weight": 1.0}, {"source": "voicemanagerstub_stubvoicemanager", "target": "voicemanagerstub_stubvoicemanager_setremotemuted", "relation": "method", "confidence": "EXTRACTED", "source_file": "C:\\projects\\ui optimization\\Trip-Sync\\mobile\\src\\lib\\voiceManagerStub.ts", "source_location": "L45", "weight": 1.0}, {"source": "voicemanagerstub_stubvoicemanager", "target": "voicemanagerstub_stubvoicemanager_getconnectedriders", "relation": "method", "confidence": "EXTRACTED", "source_file": "C:\\projects\\ui optimization\\Trip-Sync\\mobile\\src\\lib\\voiceManagerStub.ts", "source_location": "L47", "weight": 1.0}], "raw_calls": []}